AIGuard/__init__.py
AIGuard-0.1.1.dist-info/LICENSE
AIGuard-0.1.1.dist-info/METADATA
AIGuard-0.1.1.dist-info/WHEEL
AIGuard-0.1.1.dist-info/top_level.txt
AIGuard-0.1.1.dist-info/RECORD
