Metadata-Version: 2.1
Name: AIGuard
Version: 0.1.1
Summary: A system to protect AI from misuse and harmful inputs.
Home-page: https://github.com/SyntaxSama/AIGuard
Author: SyntaxSama
Author-email: syntaxsama@gmail.com
Classifier: Programming Language :: Python :: 3
Classifier: License :: OSI Approved :: MIT License
Classifier: Operating System :: OS Independent
Requires-Python: >=3.6
License-File: LICENSE
Requires-Dist: ollama
